gherkan/__init__.py
gherkan/__main__.py
gherkan/containers/README.md
gherkan/containers/SignalStatementTree.py
gherkan/containers/SignalStatementTreeNode.py
gherkan/containers/__init__.py
gherkan/containers/case_template_detection.py
gherkan/containers/signal_batch.py
gherkan/containers/signal_conditional_statement.py
gherkan/containers/signal_scenario.py
gherkan/containers/templates_dic.yaml
gherkan/containers/test.py
gherkan/decoder/NLParser.py
gherkan/decoder/Parser.py
gherkan/decoder/README.md
gherkan/decoder/SignalParser.py
gherkan/decoder/__init__.py
gherkan/decoder/word_morpho.py
gherkan/encoder/NL2Temp.py
gherkan/encoder/NLFileWriter.py
gherkan/encoder/README.md
gherkan/encoder/RawNLParser.py
gherkan/encoder/SignalFileWriter.py
gherkan/encoder/__init__.py
gherkan/flask_api/__init__.py
gherkan/flask_api/api_fsa.py
gherkan/flask_api/gherkan_rest.py
gherkan/flask_api/raw_text_to_signal.py
gherkan/flask_api/signal_to_nl.py
gherkan/flask_api/speech_to_text.py
gherkan/flask_api/resources/__init__.py
gherkan/flask_api/resources/actions.py
gherkan/flask_api/resources/audio.py
gherkan/flask_api/resources/handler.py
gherkan/flask_api/resources/nl_scenario.py
gherkan/flask_api/resources/nl_text.py
gherkan/flask_api/resources/signal_map.py
gherkan/flask_api/resources/signals.py
gherkan/processing/README.md
gherkan/processing/Temp2NL.py
gherkan/processing/Temp2NL_nomajka.py
gherkan/processing/TreeProcessor.py
gherkan/processing/__init__.py
gherkan/utils/RobotPrograms_cz.json
gherkan/utils/RobotPrograms_en.json
gherkan/utils/__init__.py
gherkan/utils/constants.py
gherkan/utils/dictionaryMapper.py
gherkan/utils/dicts.py
gherkan/utils/en-cz_phrases.yaml
gherkan/utils/gherkin_keywords.py
gherkan/utils/majka.l-wt
gherkan/utils/majka.lt-w
gherkan/utils/majka.w-lt
gherkan/utils/synonyms.json
gherkan/utils/templates_dic.yaml
gherkan/utils/translator.py
gherkan/utils/translator_dictionary_template.yaml
gherkan/utils/word_morpho.py
tests/README.md
tests/case_RawNLParser.py
gherkan-0.0.9a3.dist-info/LICENSE.txt
gherkan-0.0.9a3.dist-info/METADATA
gherkan-0.0.9a3.dist-info/WHEEL
gherkan-0.0.9a3.dist-info/dependency_links.txt
gherkan-0.0.9a3.dist-info/top_level.txt
gherkan-0.0.9a3.dist-info/RECORD
