Metadata-Version: 2.1
Name: gherkan
Version: 0.0.9a3
Summary: NL to Gherkin format translation tool
Home-page: UNKNOWN
Author: Imitation Learning Group CIIRC CVUT
Maintainer-email: radoslav.skoviera@cvut.cz
License: This work is licensed under the Creative Commons Attribution-ShareAlike 3.0 Unported License. To view a copy of this license, visit http://creativecommons.org/licenses/by-sa/3.0/ or send a letter to Creative Commons, PO Box 1866, Mountain View, CA 94042, USA.
Platform: UNKNOWN
Classifier: Programming Language :: Python :: 3
Classifier: Programming Language :: Python :: 3.6
Classifier: Programming Language :: Python :: 3.7
Classifier: Development Status :: 3 - Alpha
Classifier: Framework :: Flask
Classifier: Intended Audience :: Education
Classifier: Intended Audience :: Information Technology
Classifier: Intended Audience :: Science/Research
Classifier: Natural Language :: Czech
Classifier: Natural Language :: English
Classifier: Topic :: Scientific/Engineering :: Artificial Intelligence
Classifier: Topic :: Scientific/Engineering :: Human Machine Interfaces
Requires-Dist: Unidecode (==1.0.22)
Requires-Dist: majka
Requires-Dist: numpy
Requires-Dist: pyyaml
Requires-Dist: pattern
Requires-Dist: urllib3
Requires-Dist: plac
Requires-Dist: requests
Requires-Dist: ujson
Requires-Dist: thinc
Requires-Dist: chardet
Requires-Dist: idna
Requires-Dist: msgpack
Requires-Dist: toolz
Requires-Dist: cymem (==1.31.2)
Requires-Dist: spacy (==2.0.13)
Requires-Dist: flask (>=1.0.2)
Requires-Dist: flask-restful (>=0.3.6)
Requires-Dist: SpeechRecognition
Requires-Dist: termcolor
Requires-Dist: en-coref-md (==3.0.0)
